LICENSE
sdgclassification/benchmark/resources/benchmark.csv
sdgclassification/benchmark/Benchmark.py
sdgclassification/benchmark/Metrics.py
sdgclassification/benchmark/Result.py
sdgclassification/benchmark/ResultSet.py
sdgclassification/benchmark/Stats.py
sdgclassification/benchmark/__init__.py
sdgclassification/benchmark/load_benchmark_df.py
sdgclassification/benchmark/py.typed
sdgclassification/benchmark/resources/__init__.py
sdgclassification_benchmark-1.0.0.dist-info/LICENSE
sdgclassification_benchmark-1.0.0.dist-info/METADATA
sdgclassification_benchmark-1.0.0.dist-info/WHEEL
sdgclassification_benchmark-1.0.0.dist-info/RECORD
