Metadata-Version: 2.1
Name: sdgclassification-benchmark
Version: 1.0.0
Summary: The SDG Classification Benchmark is an open and public resource for evaluating and comparing SDG classification models.
Home-page: https://github.com/SDGClassification/benchmark
License: MIT
Author: Finn Woelm
Author-email: finn@globalgoals.directory
Requires-Python: >=3.9,<4.0
Classifier: License :: OSI Approved :: MIT License
Classifier: Programming Language :: Python :: 3
Classifier: Programming Language :: Python :: 3.9
Classifier: Programming Language :: Python :: 3.10
Classifier: Programming Language :: Python :: 3.11
Classifier: Programming Language :: Python :: 3.12
Requires-Dist: pandas (>=2.2.2,<3.0.0)
Requires-Dist: progress (>=1.6,<2.0)
Requires-Dist: tabulate (>=0.9.0,<0.10.0)
Project-URL: Repository, https://github.com/SDGClassification/benchmark
